srcmlmal/__init__.py
srcmlmal/config.py
srcmlmal/dataset.py
srcmlmal/features.py
srcmlmal/modeling/__init__.py
srcmlmal/modeling/predict.py
srcmlmal/modeling/train.py
srcmlmal/modeling/trainer.py
srcmlmal-0.0.2.dist-info/LICENSE
srcmlmal-0.0.2.dist-info/WHEEL
srcmlmal-0.0.2.dist-info/METADATA
srcmlmal-0.0.2.dist-info/RECORD
