Metadata-Version: 2.3
Name: srcmlmal
Version: 0.0.2
Summary: mlops course repo
Author: mmmhdp
Requires-Python: ~=3.12
Classifier: Programming Language :: Python :: 3
Classifier: License :: OSI Approved :: MIT License
